xjpath
