Metadata-Version: 1.1
Name: xjpath
Version: 0.1.5
Summary: JSON like structure data lookup library. A fast alternative to XPath and JsonPath. Python3 only.
Home-page: https://github.com/vburenin/xjpath
Author: Volodymyr Burenin
Author-email: vburenin@gmail.com
License: MIT
Platform: UNKNOWN
Classifier: License :: OSI Approved :: MIT License
Classifier: Development Status :: 5 - Production/Stable
Classifier: Intended Audience :: Developers
Classifier: Programming Language :: Python :: 3.2
Classifier: Programming Language :: Python :: 3.3
Classifier: Programming Language :: Python :: 3.4
Classifier: Topic :: Software Development :: Libraries :: Python Modules
